contxt/__init__.py
contxt/logger.py
contxt/repo_flattener.py
contxt-0.1.3.dist-info/METADATA
contxt-0.1.3.dist-info/WHEEL
contxt-0.1.3.dist-info/entry_points.txt
contxt-0.1.3.dist-info/RECORD
