Metadata-Version: 2.4
Name: contxt
Version: 0.1.3
Summary: A CLI utility for analyzing and flattening contextual informationinto consolidated files with metadata.
Requires-Python: >=3.11
Requires-Dist: alembic>=1.14.0
Requires-Dist: click>=8.1.8
Requires-Dist: fastapi>=0.115.6
Requires-Dist: loguru>=0.7.3
Requires-Dist: psycopg2-binary>=2.9.10
Requires-Dist: python-dotenv>=1.0.1
Requires-Dist: uvicorn>=0.34.0
